cloudflare_challenge/__init__.py
cloudflare_challenge/mailer.py
cloudflare_challenge/view.py
cloudflare_challenge/templates/cloudflare-challenge.html
cloudflare_challenge/templates/cloudflare-iframe.html
cloudflare_challenge/templates/cloudflare-iframe.js
cloudflare_challenge/templates/cloudflare-macros.html
cloudflare_challenge/templates/cloudflare-main.html
cloudflare_challenge-0.1.6.dist-info/METADATA
cloudflare_challenge-0.1.6.dist-info/WHEEL
cloudflare_challenge-0.1.6.dist-info/licenses/LICENSE
cloudflare_challenge-0.1.6.dist-info/RECORD
