Metadata-Version: 2.4
Name: cloudflare-challenge
Version: 0.1.6
Summary: CloudFlare Challenge pages
Author-email: arabidopsis <ian.castleden@gmail.com>
License-File: LICENSE
Requires-Python: >=3.10
Requires-Dist: flask<4,>=2.0
